README.rst
setup.py
RQ_Cron.egg-info/PKG-INFO
RQ_Cron.egg-info/SOURCES.txt
RQ_Cron.egg-info/dependency_links.txt
RQ_Cron.egg-info/entry_points.txt
RQ_Cron.egg-info/requires.txt
RQ_Cron.egg-info/top_level.txt
rq_cron/__init__.py
rq_cron/scripts/__init__.py
rq_cron/scripts/rq_cron.py