Metadata-Version: 1.0
Name: RQ-Cron
Version: 1.0.1
Summary: RQ Cron
Home-page: https://github.com/Healthjoy/rq-cron
Author: Andrii Kostenko
Author-email: andrey@kostenko.name
License: UNKNOWN
Platform: UNKNOWN
